redbrick_sagemaker/VERSION
redbrick_sagemaker/__init__.py
redbrick_sagemaker/logging.py
redbrick_sagemaker/active_learning/__init__.py
redbrick_sagemaker/active_learning/active_learning_test.py
redbrick_sagemaker/active_learning/public.py
redbrick_sagemaker/sagemaker_client/__init__.py
redbrick_sagemaker/sagemaker_client/public.py
redbrick_sagemaker/utils/__init__.py
redbrick_sagemaker/utils/bbox.py
redbrick_sagemaker/utils/dataio.py
redbrick_sagemaker/utils/im2rec.py
redbrick_sagemaker/utils/redbrick.py
redbrick_sagemaker/utils/sagemaker.py
redbrick_sagemaker-0.0.4.dist-info/LICENSE
redbrick_sagemaker-0.0.4.dist-info/METADATA
redbrick_sagemaker-0.0.4.dist-info/WHEEL
redbrick_sagemaker-0.0.4.dist-info/top_level.txt
redbrick_sagemaker-0.0.4.dist-info/RECORD
