Metadata-Version: 2.1
Name: redbrick-sagemaker
Version: 0.0.4
Summary: RedBrick AI and AWS Sagemaker integration
Home-page: https://github.com/redbrick-ai/redbrick-sagemaker
License: UNKNOWN
Platform: UNKNOWN
Requires-Python: >=3.7.0, <3.10
License-File: LICENSE
Requires-Dist: redbrick-sdk (>=0.6.13)
Requires-Dist: sagemaker (==2.60.0)
Requires-Dist: boto3 (==1.20.11)
Requires-Dist: mxnet (>=1.5.0)
Requires-Dist: opencv-python (==4.5.4.60)
Provides-Extra: dev
Requires-Dist: wheel (==0.35.1) ; extra == 'dev'
Requires-Dist: pytest-mock (==3.3.1) ; extra == 'dev'
Requires-Dist: pytest (==6.1.2) ; extra == 'dev'
Requires-Dist: black (==21.7b0) ; extra == 'dev'
Requires-Dist: mypy (==0.790) ; extra == 'dev'
Requires-Dist: mypy-extensions (==0.4.3) ; extra == 'dev'
Requires-Dist: pylint (==2.11.1) ; extra == 'dev'
Requires-Dist: pycodestyle (==2.6.0) ; extra == 'dev'
Requires-Dist: pydocstyle (==5.1.1) ; extra == 'dev'
Requires-Dist: flake8 (==3.8.4) ; extra == 'dev'
Requires-Dist: flake8-print (==3.1.4) ; extra == 'dev'
Requires-Dist: eradicate (==1.0) ; extra == 'dev'
Requires-Dist: pytest-cov (>=2.8.1) ; extra == 'dev'
Requires-Dist: pytest-asyncio (==0.12.0) ; extra == 'dev'
Requires-Dist: pytest-eradicate (==0.0.5) ; extra == 'dev'
Requires-Dist: pytest-pycodestyle (==2.2.0) ; extra == 'dev'
Requires-Dist: pytest-pydocstyle (==2.2.0) ; extra == 'dev'
Requires-Dist: pytest-black (==0.3.12) ; extra == 'dev'
Requires-Dist: pytest-pylint (==0.17.0) ; extra == 'dev'
Requires-Dist: pytest-mypy (==0.7.0) ; extra == 'dev'
Requires-Dist: pytest-flake8 (==1.0.6) ; extra == 'dev'
Requires-Dist: pytest-randomly (==3.4.1) ; extra == 'dev'
